{
    "Ads": [
      {
        "select_main_ads": "ADMOB",
        "select_backup_ads":"APPLOVIN-D",
        "main_ads_banner": "ca-app-pub-8799090825709075/8652257235",
        "main_ads_intertitial":"ca-app-pub-8799090825709075/9707739482",
        "main_ads_natives":"",
        "backup_ads_natives":"",
        "backup_ads_banner":"",
        "backup_ads_intertitial":"",
        "open_ads_admob":"ca-app-pub-8799090825709075/3591502240",
        "open_ads_alien":"",
        "switch_open_ads":"1",
        "switch_banner_natives_ads":"",
        "interval_intertitial": 3,
        "initialize_sdk":"",
        "initialize_sdk_backup_ads":"",
        "high_paying_keyword_1": "investasi",
        "high_paying_keyword_2": "pinjaman",
        "high_paying_keyword_3": "saham",
        "high_paying_keyword_4": "crypto",
        "high_paying_keyword_5": "penghasilan",
        "status_app": "0",
        "link_redirect": "https://ptmencaricintasejati.com"
      }
   ],
    "Data": [
      {
        "id": 3,
        "name_category": "tentang Tunai Kilat Pinjol Cair Tips",
        "title": "Apa itu Tunai Kilat Pinjol Cair Tips?",
        "image": "https://blue.kumparan.com/image/upload/v1634025439/0d694e32c2ca4c2543ddfeae0183a1457aa03973884d2f974ee7dd2cbbb1af1b.jpg",
        "description": "Tentang Tunai Kilat Pinjol Cair Tips",
        "link": "Tunai Kilat Pinjol Cair mungkin mengacu pada suatu layanan pinjaman online yang menawarkan pencairan dana dengan cepat. Berikut ini beberapa tips yang dapat membantu Anda dalam menggunakan layanan pinjaman online seperti Tunai Kilat Pinjol Cair: Evaluasi kebutuhan pinjaman: Pertimbangkan dengan seksama kebutuhan Anda sebelum mengajukan pinjaman. Pastikan bahwa pinjaman tersebut benar-benar diperlukan dan akan memberikan manfaat yang sebanding dengan biaya dan bunga yang harus Anda bayar. Teliti penyedia pinjaman: Lakukan penelitian tentang penyedia layanan pinjaman online yang ingin Anda gunakan, termasuk Tunai Kilat Pinjol Cair atau penyedia lainnya. Periksa reputasi mereka, ulasan pengguna, dan keandalan layanan mereka. Pastikan untuk memilih penyedia yang tepercaya dan terpercaya. Periksa syarat dan ketentuan: Bacalah dengan seksama syarat dan ketentuan pinjaman sebelum menyetujuinya. Perhatikan suku bunga, biaya, jangka waktu pembayaran, dan denda keterlambatan. Pastikan Anda memahami sepenuhnya semua persyaratan dan konsekuensi yang terkait dengan pinjaman. Pilih jumlah pinjaman yang tepat: Hanya pinjam jumlah yang sesuai dengan kebutuhan Anda. Hindari meminjam lebih dari yang Anda butuhkan agar tidak terjebak dalam beban pembayaran yang berlebihan. Hitung kemampuan pembayaran: Perhitungkan kemampuan Anda untuk membayar cicilan pinjaman secara tepat waktu. Buatlah anggaran yang realistis dan pastikan Anda memiliki sumber dana yang cukup untuk membayar cicilan tersebut setiap bulan. Hindari pinjaman berulang: Gunakan pinjaman online dengan bijak dan hindari terjebak dalam siklus pinjaman berulang. Jika memungkinkan, usahakan untuk memperbaiki situasi keuangan Anda sehingga Anda tidak perlu terus-menerus mengandalkan pinjaman tambahan. Lindungi informasi pribadi: Pastikan Anda menggunakan layanan pinjaman online yang aman dan terpercaya. Periksa kebijakan privasi mereka dan pastikan bahwa data pribadi Anda akan dilindungi dengan baik. Gunakan pinjaman sebagai alat bantu: Gunakan pinjaman online sebagai alat bantu sementara, bukan sebagai sumber pendapatan utama. Berfokuslah pada manajemen keuangan yang baik dan upayakan untuk membangun cadangan darurat dan mengurangi ketergantungan pada pinjaman. Ingatlah bahwa tips ini bersifat umum dan Anda harus mempertimbangkan situasi keuangan pribadi Anda sendiri saat menggunakan layanan pinjaman online. Jangan ragu untuk berkonsultasi dengan ahli keuangan jika Anda memiliki pertanyaan lebih lanjut."
       },
      {
        "id": 1,
        "name_category": "Tutorial",
        "title": "Bagaimana mengajukan Tunai Kilat Pinjol Cair Tips?",
        "image": "https://cdn0-production-images-kly.akamaized.net/vESXspRYA2LNdCr595cS_aKImwQ=/640x360/smart/filters:quality(75):strip_icc():format(jpeg)/kly-media-production/medias/3341346/original/051403500_1609901936-shutterstock_1725491257.jpg",
        "description": "Cara  mengajukan Tunai Kilat Pinjol Cair Tips",
        "Link": "meminjam uang secara online atau melalui Pinjaman Online (Pinjol) memiliki risiko tertentu. Pastikan Anda membaca syarat dan ketentuan dengan teliti dan memahami semua biaya dan bunga yang terkait dengan pinjaman tersebut. Jangan pernah meminjam uang lebih dari yang Anda mampu untuk membayar kembali, dan selalu gunakan Pinjol yang resmi dan terpercaya. Namun, jika Anda memutuskan untuk menggunakan Pinjol dan ingin memperoleh pinjaman dengan cepat, berikut beberapa tips untuk Pinjol cepat cair dalam waktu 5 menit: Pilih Pinjol yang memproses aplikasi dengan cepat: Pastikan Pinjol yang Anda pilih memiliki proses persetujuan dan pencairan dana yang cepat. Banyak Pinjol menawarkan pencairan dana dalam waktu 24 jam, namun beberapa juga menawarkan pencairan dalam waktu lebih singkat, seperti 5-10 menit. Persiapkan dokumen dan informasi yang diperlukan: Pastikan Anda memiliki semua dokumen dan informasi yang diperlukan sebelum mengajukan pinjaman. Ini dapat mencakup salinan KTP, slip gaji, rekening bank, dan dokumen lain yang diminta oleh Pinjol. Dengan mempersiapkan dokumen ini sebelumnya, Anda dapat mempercepat proses aplikasi. Ajukan pinjaman di jam kerja: Sebagian besar Pinjol memproses aplikasi hanya pada jam kerja. Jadi, pastikan Anda mengajukan pinjaman Anda selama jam kerja agar aplikasi Anda diproses dengan cepat. Pilih jumlah pinjaman yang sesuai: Pinjol akan menilai penghasilan dan kemampuan Anda untuk membayar kembali pinjaman sebelum menyetujui pinjaman. Pilih jumlah pinjaman yang sesuai dengan kemampuan Anda membayar kembali pinjaman dan jangan meminjam lebih dari yang Anda butuhkan. Gunakan aplikasi Pinjol resmi dan terpercaya: Terakhir, pastikan Anda menggunakan Pinjol yang resmi dan terpercaya untuk meminimalkan risiko penipuan atau masalah lainnya. Periksa ulasan dan reputasi Pinjol sebelum mengajukan pinjaman. Dengan mengikuti tips-tips di atas, Anda dapat memperoleh pinjaman melalui Pinjol dengan cepat dan mudah, tetapi selalu ingat bahwa Anda bertanggung jawab untuk membayar kembali pinjaman tersebut dan harus mempertimbangkan segala risiko yang terkait."      
      },
      {
        "id": 2,
        "name_category": "Tutorial",
        "title": "Resiko  Tunai Kilat Pinjol Cair Tips?",
        "image": "https://solusinews.id/wp-content/uploads/2021/03/pinjaman-ilegal.jpg",
        "description": "Resiko  Tunai Kilat Pinjol Cair Tips",
        "link": "Link : Beberapa risiko yang dapat timbul dari penggunaan Pinjol OJK Mudah Cair adalah Bunga dan Biaya Tambahan yang Tinggi: Sebagian besar pinjaman online menawarkan bunga dan biaya tambahan yang lebih tinggi dibandingkan dengan pinjaman tradisional. Oleh karena itu, sebelum memutuskan untuk mengambil pinjaman, pastikan untuk membaca dengan teliti syarat dan ketentuan yang berlaku dan memperhitungkan dengan baik kemampuan finansial Anda untuk membayar kembali pinjaman tersebut. Terganggu Privasi: Beberapa perusahaan pinjaman online mungkin mengumpulkan data pribadi Anda untuk kepentingan mereka. Pastikan untuk membaca kebijakan privasi dan memastikan bahwa data pribadi Anda tidak disalahgunakan. Terjebak dalam Lingkaran Hutang: Jika tidak diatur dengan baik, pinjaman online dapat membuat seseorang terjebak dalam lingkaran hutang yang sulit diatasi. Pastikan untuk mempertimbangkan kemampuan finansial Anda dan hanya meminjam jumlah yang diperlukan serta membayar cicilan tepat waktu. Resiko Penipuan: Meskipun program Pinjol OJK Mudah Cair bekerja sama dengan perusahaan pinjaman online yang telah terdaftar dan diawasi oleh OJK, masih ada risiko penipuan oleh pihak yang tidak bertanggung jawab. Pastikan untuk memilih perusahaan pinjaman online yang terpercaya dan telah terdaftar di OJK. Resiko Gangguan Keamanan: Ada risiko gangguan keamanan atau pencurian identitas saat mengajukan pinjaman online. Pastikan untuk menggunakan jaringan internet yang aman dan memastikan bahwa informasi pribadi Anda tidak dicuri oleh pihak yang tidak bertanggung jawab. Sebelum memutuskan untuk mengajukan Pinjol OJK Mudah Cair, pastikan untuk mempertimbangkan semua risiko yang terkait dan memilih perusahaan pinjaman online yang terpercaya serta sesuai dengan kebutuhan dan kemampuan finansial Anda."
      },
      {
        "id": 4,
        "name_category": "Tutorial",
        "title": "Apa Tunai Kilat Pinjol Cair Tips?",
        "image": "https://primaradio.co.id/wp-content/uploads/2023/02/Penjelasan-Singkat-Pinjol-Ilegal-600x339.jpg",
        "description": "Apakah Bisa Cair",
        "link": "Ya, Pinjol cepat cair 5 menit tips bisa cair dalam waktu 5 menit atau lebih cepat setelah persetujuan pinjaman. Pinjol cepat cair biasanya menawarkan proses persetujuan dan pencairan dana yang cepat, dan dapat memberikan dana tunai dengan cepat untuk kebutuhan mendesak seperti biaya kesehatan, biaya pendidikan, atau kebutuhan bisnis. Namun, untuk mendapatkan Pinjol cepat cair, Anda perlu memenuhi persyaratan yang ditetapkan oleh Pinjol, seperti memiliki usia yang memenuhi syarat, memiliki pekerjaan atau penghasilan yang stabil, serta memiliki riwayat kredit yang baik. Selain itu, proses persetujuan juga memerlukan waktu untuk memverifikasi informasi dan dokumen yang Anda berikan. Sebelum mengajukan Pinjol cepat cair, pastikan Anda memilih Pinjol yang resmi dan terpercaya, serta memahami syarat dan ketentuan yang terkait dengan pinjaman tersebut. Selalu gunakan Pinjol dengan bijak dan jangan pernah meminjam lebih dari yang Anda mampu untuk membayar kembali."
      },
      {
        "id": 5,
        "name_category": "Tutorial Tunai Kilat Pinjol Cair Tips",
        "title": "Cara Tunai Kilat Pinjol Cair Tips ke Wallet",
        "image": "https://i.ytimg.com/vi/AwKEgC5rG6s/maxresdefault.jpg",
        "description": "Tunai Kilat Pinjol Cair Tips ke Wallet",
        "link": "Sebelum melakukan pinjaman online atau pinjaman online terhadap wallet, pastikan bahwa Anda telah mempertimbangkan kebutuhan finansial Anda dan telah memahami sepenuhnya biaya dan risiko yang terkait dengan pinjaman tersebut. Selain itu, pastikan juga bahwa Anda memilih pemberi pinjaman yang terpercaya dan memiliki reputasi yang baik. Berikut adalah tips untuk melakukan pinjaman online dan mencairkan dana ke wallet: Pilih platform pinjaman online yang terpercaya dan memiliki reputasi baik. Pastikan untuk membaca dan memahami syarat dan ketentuan pinjaman sebelum mengajukan pinjaman. Isi formulir aplikasi dengan benar dan lengkap, pastikan bahwa semua informasi yang diminta telah diisi dengan benar. Verifikasi identitas Anda dengan benar dan lengkap, biasanya melalui proses pengiriman foto KTP atau selfie dengan KTP di tangan. Tunggu persetujuan dan pencairan dana ke wallet Anda. Biasanya proses persetujuan dan pencairan dana memakan waktu beberapa hari, tergantung pada kebijakan pemberi pinjaman. Setelah dana telah dicairkan ke wallet Anda, pastikan untuk mengelola dan memanfaatkannya dengan bijak, sehingga Anda dapat membayar pinjaman tepat waktu dan meminimalkan risiko yang terkait dengan pinjaman tersebut. Selalu membaca syarat dan ketentuan secara teliti, dan pastikan bahwa Anda memahami semua biaya, bunga, dan kewajiban yang terkait dengan pinjaman tersebut."
      },
      {
        "id": 6,
        "name_category": "Tutorial",
        "title": "Apakah Tunai Kilat Pinjol Cair Tips?",
        "image": "https://radargroup.id/wp-content/uploads/2023/02/Pinjaman-Online-Cepat-CAIR-Cukup-KTP-Langsung-ACC.jpg",
        "description": "Apa Tunai Kilat Pinjol Cair Tips di tagih ?",
        "link": "membayar pinjaman tepat waktu dan meminimalkan risiko yang terkait dengan pinjaman. Jika Anda mengalami kesulitan dalam membayar pinjaman, segera hubungi pemberi pinjaman untuk mencari solusi yang tepat dan menghindari denda dan biaya tambahan. Pinjol OJK Mudah Cair Clue adalah program dari OJK (Otoritas Jasa Keuangan) yang bertujuan untuk memberikan kemudahan akses bagi masyarakat dalam mengakses pinjaman online yang terdaftar dan diawasi oleh OJK. Namun, meskipun program ini diawasi oleh OJK, keputusan untuk menyetujui atau menolak pinjaman serta proses pengembalian pinjaman tetap berada di tangan perusahaan pinjaman online yang terdaftar di OJK. Setelah mengajukan pinjaman dan mendapat persetujuan dari perusahaan pinjaman online, pihak perusahaan akan memberikan informasi mengenai jumlah pinjaman, jangka waktu pengembalian, bunga, biaya administrasi, dan syarat-syarat lainnya. Pada umumnya, perusahaan pinjaman online akan mengirimkan tagihan bulanan atau peringatan pembayaran melalui email, SMS, atau aplikasi perusahaan. Namun, jika Anda lupa atau tidak dapat melakukan pembayaran tepat waktu, perusahaan pinjaman online dapat membebankan biaya keterlambatan atau mengambil tindakan lain sesuai dengan ketentuan yang telah disepakati. Oleh karena itu, sangat penting untuk membaca dengan teliti semua syarat dan ketentuan yang berlaku sebelum mengajukan pinjaman dan memastikan bahwa Anda mampu untuk memenuhi kewajiban pembayaran pinjaman tepat waktu. Dengan begitu, Anda dapat menghindari masalah tagihan yang tidak teratur dan menjaga kesehatan keuangan Anda."
      },
      {
        "id": 7,
        "name_category": "Tutorial",
        "title": "Rekomendasi Tunai Kilat Pinjol Cair Tips?",
        "image": "https://pindahlubang.com/wp-content/uploads/2021/11/th-124.jpeg",
        "description": "Ini Tunai Kilat Pinjol Cair Tips Rekomendasinya",
        "description": "Ini  Rekomendasinya",
        "link": "Namun, jika Anda memerlukan saran tentang pinjaman online yang cepat cair, pastikan untuk memilih pemberi pinjaman yang terpercaya dan memiliki reputasi baik. Selalu baca dan pahami dengan cermat semua syarat dan ketentuan, serta biaya dan bunga yang terkait dengan pinjaman tersebut. Selain itu, pastikan bahwa Anda dapat membayar pinjaman tepat waktu dan menghindari penalti dan biaya tambahan. Jangan pernah meminjam uang lebih dari yang Anda butuhkan atau yang tidak dapat Anda bayar kembali. Akhirnya, jika Anda mengalami kesulitan dalam membayar pinjaman, segera hubungi pemberi pinjaman untuk mencari solusi yang tepat dan menghindari denda dan biaya tambahan. Jadi, sebagai kesimpulan, saya tidak dapat merekomendasikan praktik-praktik yang tidak etis atau ilegal. Namun, saya menyarankan agar Anda selalu memilih pemberi pinjaman yang terpercaya, membaca dan memahami dengan cermat syarat dan ketentuan, serta menghindari risiko yang terkait dengan pinjaman. Periksa daftar perusahaan pinjaman online yang terdaftar di situs resmi OJK. Pastikan perusahaan pinjaman online yang akan Anda ajukan pinjaman terdaftar dan diawasi oleh OJK untuk memastikan legalitas dan keamanan transaksi. Periksa bunga dan biaya yang dikenakan oleh perusahaan pinjaman online. Pastikan untuk memperhatikan bunga, biaya administrasi, dan biaya lainnya yang dikenakan oleh perusahaan pinjaman online dan membandingkannya dengan perusahaan lain untuk memastikan bahwa Anda memilih yang terbaik sesuai dengan kebutuhan dan kemampuan finansial Anda. Periksa syarat dan ketentuan pinjaman. Pastikan untuk membaca dengan teliti semua syarat dan ketentuan yang berlaku, termasuk jangka waktu pinjaman, cara pembayaran, dan sanksi yang diberlakukan jika Anda tidak dapat membayar pinjaman tepat waktu. Periksa reputasi perusahaan pinjaman online. Pastikan untuk mencari informasi tentang reputasi perusahaan pinjaman online tersebut dengan mencari ulasan dan pengalaman dari pengguna lain di internet. Dengan mempertimbangkan tips di atas, Anda dapat memilih perusahaan pinjaman online yang terdaftar dan diawasi oleh OJK dengan bunga dan biaya yang terjangkau dan sesuai dengan kemampuan finansial Anda. Namun, tetap ingat untuk mengajukan pinjaman sesuai dengan kebutuhan dan kemampuan finansial Anda agar tidak terlilit hutang yang tidak terbayar."
      },
      {
        "id": 8,
        "name_category": "Tutorial",
        "title": "keuntungan menggunakan Tunai Kilat Pinjol Cair Tips?",
        "image": "https://danakoo.id/wp-content/uploads/2022/12/kta-kilat.jpg",
        "description": "Berikut ini beberapa keuntungannya Tunai Kilat Pinjol Cair Tips yang perlu kamu ketahui.",
        "link": "Pinjaman online atau Pinjol Cepat Cair memang memiliki beberapa keuntungan dibandingkan dengan pinjaman tradisional. Berikut adalah beberapa keuntungan menggunakan Pinjol Cepat Cair: Proses pengajuan yang mudah dan cepat: Proses pengajuan untuk pinjol cepat cair dapat dilakukan secara online dengan mengisi formulir aplikasi dan verifikasi identitas. Proses ini dapat dilakukan dalam waktu yang relatif cepat, sehingga Anda bisa mendapatkan dana yang dibutuhkan dalam waktu singkat. Tanpa jaminan: Banyak Pinjol Cepat Cair yang tidak memerlukan jaminan untuk mengajukan pinjaman. Hal ini memudahkan orang yang tidak memiliki jaminan untuk mendapatkan pinjaman. Tersedia untuk semua orang: Pinjol Cepat Cair tersedia untuk semua orang, baik itu pekerja formal, wiraswasta, atau bahkan mahasiswa. Selama Anda memenuhi persyaratan yang ditetapkan oleh pemberi pinjaman, Anda dapat mengajukan pinjaman. Bunga yang kompetitif: Beberapa Pinjol Cepat Cair menawarkan bunga yang kompetitif, bahkan lebih rendah daripada bunga pada pinjaman tradisional. Fleksibilitas dalam penggunaan dana: Pinjol Cepat Cair umumnya tidak membatasi penggunaan dana yang dipinjam, sehingga Anda dapat menggunakan dana tersebut untuk berbagai keperluan seperti membayar tagihan, membeli barang, atau membiayai kebutuhan darurat. Meskipun Pinjol Cepat Cair memiliki beberapa keuntungan, namun pastikan untuk memilih pemberi pinjaman yang terpercaya dan memiliki reputasi baik serta membaca dan memahami dengan cermat semua syarat dan ketentuan, serta biaya dan bunga yang terkait dengan pinjaman tersebut. Selalu pastikan bahwa Anda dapat membayar pinjaman tepat waktu dan menghindari penalti dan biaya tambahan."
      },
      {
        "id": 9,
        "name_category": "Tutorial",
        "title": "Kerugian Tunai Kilat Pinjol Cair Tips",
        "image": "https://i.ytimg.com/vi/AwKEgC5rG6s/maxresdefault.jpg",
        "description": "Berikut kerugiannya Tunai Kilat Pinjol Cair Tips",
        "link": "Meskipun Pinjol Cepat Cair memiliki beberapa keuntungan, namun ada beberapa kerugian yang perlu dipertimbangkan sebelum memutuskan untuk mengambil pinjaman online, di antaranya: Bunga dan biaya yang tinggi: Beberapa Pinjol Cepat Cair menerapkan bunga dan biaya yang tinggi, sehingga Anda mungkin membayar lebih mahal daripada jika mengambil pinjaman dari bank atau lembaga keuangan tradisional. Risiko penipuan: Terdapat risiko penipuan dan keamanan yang harus diwaspadai ketika mengambil pinjaman online. Pastikan untuk memilih pemberi pinjaman yang terpercaya dan memiliki reputasi baik, serta membaca dan memahami dengan cermat semua syarat dan ketentuan. Pinjaman berulang-ulang: Beberapa orang mungkin terjebak dalam siklus pinjaman berulang-ulang karena kesulitan membayar pinjaman sebelumnya. Hal ini dapat menyebabkan Anda terjebak dalam hutang yang semakin bertambah. Dampak pada skor kredit: Jika Anda gagal membayar pinjaman online, hal ini dapat berdampak pada skor kredit Anda, yang dapat membuat sulit untuk meminjam uang di masa depan. Ketergantungan pada pinjaman: Pinjaman online dapat membuat Anda tergantung pada pinjaman untuk memenuhi kebutuhan finansial, yang dapat menyebabkan masalah keuangan jangka panjang. Jadi, sebelum mengambil pinjaman online, pastikan untuk mempertimbangkan dengan cermat semua kerugian yang terkait dengan pinjaman tersebut. Selalu pilih pemberi pinjaman yang terpercaya dan memiliki reputasi baik, serta membaca dan memahami dengan cermat semua syarat dan ketentuan, serta biaya dan bunga yang terkait dengan pinjaman tersebut."
      },
      {
        "id": 10,
        "name_category": "Tutorial",
        "title": "Hadist Tentang  Tunai Kilat Pinjol Cair Tips",
        "image": "https://i0.wp.com/www.biem.co/wp-content/uploads/2021/01/ilustrasi-pinjaman-online.jpg",
        "description": "Ini Hadistnya Tunai Kilat Pinjol Cair Tips",
        "link": "Riba dalam berpiutang adalah sebuah penambahan nilai atau bunga melebihi jumlah pinjaman saat dikembalikan dengan nilai tertentu yang diambil dari jumlah pokok pinjaman untuk dibayarkan oleh peminjam. Larangan (keharaman) praktik riba disebut secara eksplisit (shorih) dalam Al-Quran, Allah telah menghalalkan jual beli dan mengharamkan riba (Al-Baqarah [2]: 275).Hukum menunda untuk membayar hutang jika sudah mampu hukum haram. Rasulullah shollallahu alaihi wasallam bersabda, Menunda-nunda (pembayaran) yang dilakukan oleh orang mampu menghalalkan harga diri dan pemberian sanksi kepadanya (HR. Nasa’i) Dalam hadis riwayat Imam Bukhori disebutkan, Penundaan (pembayaran) yang dilakukan oleh orang mampu adalah suatu kezaliman (HR. Bukhori)."
      }
    ]
  }
